setup.py
battery_status/__init__.py
battery_status/command_line.py
battery_status.egg-info/PKG-INFO
battery_status.egg-info/SOURCES.txt
battery_status.egg-info/dependency_links.txt
battery_status.egg-info/entry_points.txt
battery_status.egg-info/not-zip-safe
battery_status.egg-info/requires.txt
battery_status.egg-info/top_level.txt