Metadata-Version: 1.0
Name: battery-status
Version: 0.0.9
Summary: Battery Status Notifier
Home-page: https://github.com/ManrajGrover/battery_status
Author: Manraj Singh
Author-email: manrajsinghgrover@gmail.com
License: MIT
Keywords: battery status notifier windows check battery status python
Platform: UNKNOWN
